odoo/addons/l10n_nl_tax_statement_icp/README.rst
odoo/addons/l10n_nl_tax_statement_icp/__init__.py
odoo/addons/l10n_nl_tax_statement_icp/__manifest__.py
odoo/addons/l10n_nl_tax_statement_icp/i18n/l10n_nl_tax_statement_icp.pot
odoo/addons/l10n_nl_tax_statement_icp/i18n/nl.po
odoo/addons/l10n_nl_tax_statement_icp/models/__init__.py
odoo/addons/l10n_nl_tax_statement_icp/models/l10n_nl_vat_statement.py
odoo/addons/l10n_nl_tax_statement_icp/models/l10n_nl_vat_statement_icp_line.py
odoo/addons/l10n_nl_tax_statement_icp/readme/CONFIGURE.md
odoo/addons/l10n_nl_tax_statement_icp/readme/CONTRIBUTORS.md
odoo/addons/l10n_nl_tax_statement_icp/readme/DESCRIPTION.md
odoo/addons/l10n_nl_tax_statement_icp/readme/ROADMAP.md
odoo/addons/l10n_nl_tax_statement_icp/readme/USAGE.md
odoo/addons/l10n_nl_tax_statement_icp/report/__init__.py
odoo/addons/l10n_nl_tax_statement_icp/report/l10n_nl_tax_statement_icp_xlsx.py
odoo/addons/l10n_nl_tax_statement_icp/report/report_tax_statement.xml
odoo/addons/l10n_nl_tax_statement_icp/security/ir.model.access.csv
odoo/addons/l10n_nl_tax_statement_icp/static/description/icon.png
odoo/addons/l10n_nl_tax_statement_icp/static/description/index.html
odoo/addons/l10n_nl_tax_statement_icp/tests/__init__.py
odoo/addons/l10n_nl_tax_statement_icp/tests/test_l10n_nl_tax_statement_icp.py
odoo/addons/l10n_nl_tax_statement_icp/views/l10n_nl_vat_statement_view.xml
odoo/addons/l10n_nl_tax_statement_icp/views/report_tax_statement.xml
odoo_addon_l10n_nl_tax_statement_icp-18.0.1.0.0.2.dist-info/METADATA
odoo_addon_l10n_nl_tax_statement_icp-18.0.1.0.0.2.dist-info/WHEEL
odoo_addon_l10n_nl_tax_statement_icp-18.0.1.0.0.2.dist-info/top_level.txt
odoo_addon_l10n_nl_tax_statement_icp-18.0.1.0.0.2.dist-info/RECORD
